plotgraph/GET.py
plotgraph/__init__.py
gsheet_plots-0.0.0.dist-info/License
gsheet_plots-0.0.0.dist-info/METADATA
gsheet_plots-0.0.0.dist-info/WHEEL
gsheet_plots-0.0.0.dist-info/top_level.txt
gsheet_plots-0.0.0.dist-info/RECORD
