Metadata-Version: 2.1
Name: gsheet-plots
Version: 0.0.0
Summary: gsheet will help to create your connection between google sheet and python through API and help to plot graph by you choice
Home-page: https://github.com/abhii1/gsheetplot
Author: abhishek pratap singh
Author-email: abhisheklumiamicro@gmail.com
License: UNKNOWN
Platform: UNKNOWN
Classifier: Programming Language :: Python :: 3
Classifier: Programming Language :: Python :: 3.6
Classifier: Operating System :: OS Independent
Requires-Python: >=3.6
Requires-Dist: gspread
Requires-Dist: oauth2client
